{
    "stats": {
        "pfpgopp": "15.0",
        "fgmpm": "39.8",
        "dqpmopp": "0.0",
        "g1opp": "41",
        "fgaopp": "73",
        "mrebpm": "11.650485436893204",
        "ftppg": "8.0-17.0",
        "tpossopp": "89.500",
        "ftppm": "7.8-16.5",
        "fgmpg": "41.0",
        "ftapgopp": "23.0",
        "mrebpg": "12.0",
        "atopp": "0",
        "drebopp": "28",
        "ftptopp": "73.9",
        "minpgopp": "206",
        "ptsoppseasonxml": "96.0",
        "rebmg": "12",
        "astpgopp": "19.0",
        "fgptg3": ".333",
        "oeff": "1.170",
        "fgpt3pct": ".333",
        "stl": "12",
        "fgp3opp": "15-37",
        "stlpgopp": "6.0",
        "trebpgopp": "38.0",
        "deff": "1.073",
        "mreb": "12.0",
        "at": "0",
        "fgp3pmopp": "14.6-35.9",
        "fgppgopp": "32.0-73.0",
        "ftmpgopp": "17.0",
        "fgm3pmopp": "14.6",
        "ftapm": "16.5",
        "ftmpg": "8.0",
        "ptspg": "100.0",
        "pfpm": "25.2",
        "fga3pg": "30.0",
        "ptspm": "97.1",
        "gaopp": "1",
        "ftmpm": "7.8",
        "fgptg": ".488",
        "fta": "17",
        "min": "206",
        "fgptg3opp": ".405",
        "ftmopp": "17",
        "fgpt3opp": "40.5",
        "fga3pm": "29.1",
        "ftapg": "17.0",
        "pfpg": "26.0",
        "fga3": "30",
        "ftm": "8",
        "astpmopp": "18.4",
        "blk": "0",
        "trebpmopp": "36.9",
        "ftpt": "47.1",
        "orebpm": "17.5",
        "ftp": "8-17",
        "tomg": "-4",
        "dqpm": "0.970873786407767",
        "stlpmopp": "5.8",
        "orebpg": "18.0",
        "dqpg": "1.0",
        "fgp3": "10-30",
        "fgp3pgopp": "15.0-37.0",
        "fgpopp": "32-73",
        "fgapm": "81.6",
        "ptspmopp": "93.2",
        "astpm": "28.2",
        "astpg": "29.0",
        "ngpatna": "0-0",
        "stlopp": "6",
        "pfpmopp": "14.6",
        "fgapg": "84.0",
        "to": "11",
        "fga3pmopp": "35.9",
        "ast": "29",
        "fgpt3": "33.3",
        "dreb": "32",
        "topg": "11.0",
        "tposs": "85.500",
        "neff": "0.097",
        "ftptg": ".471",
        "ftptgopp": ".739",
        "blkpm": "0.0",
        "dq": "1",
        "orebpmopp": "9.7",
        "topm": "10.7",
        "fgmopp": "32",
        "blkpg": "0.0",
        "atoopp": "1.3",
        "fgm3pgopp": "15.0",
        "fgptpctopp": ".438",
        "blkpmopp": "4.9",
        "atn": "0.0",
        "ftppct": ".471",
        "ato": "2.6",
        "gsopp": "1",
        "fgapgopp": "73.0",
        "pfopp": "15",
        "ptspgopp": "96.0",
        "ftpopp": "17-23",
        "drebpmopp": "27.2",
        "g1": "55",
        "fgpt": "48.8",
        "topgopp": "15.0",
        "g2": "45",
        "trebopp": "38",
        "fgp3pm": "9.7-29.1",
        "treb": "50",
        "trebpm": "48.5",
        "fga3opp": "37",
        "ftppgopp": "17.0-23.0",
        "ptsgamexml": "100.0",
        "dqopp": "0",
        "ptsoppgamexml": "96.0",
        "fgpt3pctopp": ".405",
        "fgmpgopp": "32.0",
        "trebpg": "50.0",
        "fga3pgopp": "37.0",
        "fga": "84",
        "fgppm": "39.8-81.6",
        "toopp": "15",
        "orebpgopp": "10.0",
        "gpopp": "1",
        "fgm3": "10",
        "fgm3pm": "9.7",
        "fgppg": "41.0-84.0",
        "fgm": "41",
        "fgp": "41-84",
        "blkpgopp": "5.0",
        "fgptopp": "43.8",
        "fgp3pg": "10.0-30.0",
        "ptsopp": "96",
        "ga": "1",
        "gpata": "0-0",
        "ftppctopp": ".739",
        "scmg": "4",
        "drebpgopp": "28.0",
        "minpmopp": "40",
        "ftaopp": "23",
        "stlpm": "11.7",
        "fgptpct": ".488",
        "gpataopp": "0-0",
        "minopp": "206",
        "fgptgopp": ".438",
        "g2opp": "55",
        "stlpg": "12.0",
        "gp": "1",
        "gs": "1",
        "topmopp": "14.6",
        "pts": "100",
        "fgapmopp": "70.9",
        "ptsseasonxml": "100.0",
        "blkopp": "5",
        "fgmpmopp": "31.1",
        "ftapmopp": "22.3",
        "fgm3pg": "10.0",
        "drebpm": "31.1",
        "oreb": "18",
        "fgppmopp": "31.1-70.9",
        "pf": "26",
        "orebopp": "10",
        "dqpgopp": "0.0",
        "ftppmopp": "16.5-22.3",
        "minpg": "206",
        "drebpg": "32.0",
        "ftmpmopp": "16.5",
        "astopp": "19",
        "minpm": "40",
        "fgm3opp": "15"
    },
    "eventDateFormatted": "Dec 13",
    "boxScoreLink": "20251213_flpp.xml",
    "event": {
        "teams": [
            {
                "name": "Northwest Mississippi Community College",
                "result": "100",
                "teamId": "rvcq26nfprhhr9au",
                "winner": false,
                "cleanName": "northwest mississippi community col"
            },
            {
                "name": "Dyersburg State Community College",
                "result": "96",
                "teamId": "7srrm0bwvfuovgn1",
                "winner": false,
                "cleanName": "dyersburg st community col"
            }
        ],
        "status": "Final",
        "notes": "",
        "notesShared": "",
        "date": 1765659600000,
        "localTimeZone": "America/Chicago",
        "tba": false,
        "home": false,
        "overall": true,
        "conference": false,
        "division": false,
        "regional": false,
        "national": true,
        "inProgress": false,
        "statusCode": 0,
        "cancelled": false,
        "postponed": false,
        "postseason": false,
        "sport": "Basketball",
        "statusRuleCode": 0,
        "neutralSite": "",
        "links": [],
        "statcrewGameID": "",
        "eventId": "flppavaqfgsf2cjr",
        "fastdate": 1765659600000,
        "streams": [
            {
                "type": 0,
                "provider": ""
            }
        ],
        "address": "",
        "city": "Dyersburg",
        "stateCountry": "Tennessee",
        "zipCode": "",
        "venue": "",
        "primetime": false,
        "forfeitHome": false,
        "forfeitAway": false,
        "weatherDelay": false,
        "suspended": false,
        "noContest": false,
        "eventType": {
            "code": "regular",
            "description": "Regular Season",
            "statsCount": true
        },
        "conferenceResult": "100-96",
        "resultAsObject": {
            "results": [
                100,
                96
            ],
            "winner": {
                "name": "Northwest Mississippi Community College",
                "result": "100",
                "teamId": "rvcq26nfprhhr9au",
                "winner": false,
                "cleanName": "northwest mississippi community col"
            },
            "loser": {
                "name": "Dyersburg State Community College",
                "result": "96",
                "teamId": "7srrm0bwvfuovgn1",
                "winner": false,
                "cleanName": "dyersburg st community col"
            },
            "resolved": true,
            "hasScores": true,
            "numericResults": [
                100,
                96
            ],
            "description": "Win",
            "score": "100-96",
            "winnerLoser": "100-96",
            "descriptionShortWithOT": "W"
        },
        "opponent": {
            "name": "Dyersburg State Community College",
            "result": "96",
            "teamId": "7srrm0bwvfuovgn1",
            "winner": false,
            "cleanName": "dyersburg st community col"
        },
        "us": {
            "name": "Northwest Mississippi Community College",
            "result": "100",
            "teamId": "rvcq26nfprhhr9au",
            "winner": false,
            "cleanName": "northwest mississippi community col"
        },
        "winner": {
            "name": "Northwest Mississippi Community College",
            "result": "100",
            "teamId": "rvcq26nfprhhr9au",
            "winner": false,
            "cleanName": "northwest mississippi community col"
        },
        "loser": {
            "name": "Dyersburg State Community College",
            "result": "96",
            "teamId": "7srrm0bwvfuovgn1",
            "winner": false,
            "cleanName": "dyersburg st community col"
        },
        "apresult": "W, 100-96",
        "ap2Result": "W, 100-96",
        "result": {
            "results": [
                100,
                96
            ],
            "winner": {
                "name": "Northwest Mississippi Community College",
                "result": "100",
                "teamId": "rvcq26nfprhhr9au",
                "winner": false,
                "cleanName": "northwest mississippi community col"
            },
            "loser": {
                "name": "Dyersburg State Community College",
                "result": "96",
                "teamId": "7srrm0bwvfuovgn1",
                "winner": false,
                "cleanName": "dyersburg st community col"
            },
            "resolved": true,
            "hasScores": true,
            "numericResults": [
                100,
                96
            ],
            "description": "Win",
            "score": "100-96",
            "winnerLoser": "100-96",
            "descriptionShortWithOT": "W"
        }
    },
    "eventDateFormattedAriaLabel": "December 13 04:00 PM:"
}