{
    "stats": {},
    "eventDateFormatted": "Jan 24",
    "boxScoreLink": "20260124_2115.xml",
    "event": {
        "teams": [
            {
                "name": "Air Force Prep",
                "result": "",
                "teamId": "no8i8v9aaxsiw4tf",
                "winner": false,
                "cleanName": "air force prep"
            },
            {
                "name": "Fort Hays Tech Northwest",
                "result": "",
                "teamId": "vxc4dwl1888maiyg",
                "winner": false,
                "cleanName": "fort hays tech northwest"
            }
        ],
        "status": "",
        "notes": "",
        "notesShared": "Max L. Jones Fieldhouse | Goodland, KS",
        "date": 1769277600000,
        "localTimeZone": "America/Denver",
        "tba": false,
        "home": true,
        "overall": true,
        "conference": false,
        "division": false,
        "regional": false,
        "national": false,
        "inProgress": false,
        "statusCode": -2,
        "cancelled": false,
        "postponed": false,
        "postseason": false,
        "sport": "Basketball",
        "statusRuleCode": 0,
        "neutralSite": "",
        "links": [],
        "statcrewGameID": "",
        "eventId": "2115o9znjtmhmjdw",
        "fastdate": 1769277600000,
        "streams": [
            {
                "type": 0,
                "provider": "prestosports"
            }
        ],
        "address": "",
        "city": "",
        "stateCountry": "",
        "zipCode": "",
        "venue": "",
        "primetime": true,
        "forfeitHome": false,
        "forfeitAway": false,
        "weatherDelay": false,
        "suspended": false,
        "noContest": false,
        "eventType": {
            "code": "regular",
            "description": "Regular Season",
            "statsCount": true
        },
        "apresult": "",
        "ap2Result": "",
        "conferenceResult": "",
        "resultAsObject": {
            "resolved": false,
            "hasScores": false,
            "description": "",
            "score": "",
            "numericResults": [],
            "winnerLoser": "",
            "descriptionShortWithOT": ""
        },
        "opponent": {
            "name": "Air Force Prep",
            "result": "",
            "teamId": "no8i8v9aaxsiw4tf",
            "winner": false,
            "cleanName": "air force prep"
        },
        "us": {
            "name": "Fort Hays Tech Northwest",
            "result": "",
            "teamId": "vxc4dwl1888maiyg",
            "winner": false,
            "cleanName": "fort hays tech northwest"
        },
        "result": {
            "resolved": false,
            "hasScores": false,
            "description": "",
            "score": "",
            "numericResults": [],
            "winnerLoser": "",
            "descriptionShortWithOT": ""
        }
    },
    "eventDateFormattedAriaLabel": "January 24 01:00 PM:"
}