{
    "stats": {},
    "eventDateFormatted": "Mar 10",
    "boxScoreLink": "20260310_dsy4.xml",
    "event": {
        "teams": [
            {
                "name": "Mississippi Gulf Coast Community College",
                "result": "",
                "teamId": "jxkq4mk8bbhnvbfe",
                "winner": false,
                "cleanName": "mississippi gulf coast community col"
            },
            {
                "name": "NJCAA Region 23 Tournament Semifinal",
                "result": "",
                "teamId": "5f1dn27b5e8a1zz3",
                "winner": false,
                "cleanName": "njcaa region tournament semifinal"
            }
        ],
        "status": "",
        "notes": "",
        "notesShared": "MACCC Champion Hosts",
        "date": 1773115200000,
        "localTimeZone": "America/Chicago",
        "tba": true,
        "home": false,
        "overall": true,
        "conference": false,
        "division": false,
        "regional": false,
        "national": true,
        "inProgress": false,
        "statusCode": -2,
        "cancelled": false,
        "postponed": false,
        "postseason": true,
        "sport": "Basketball",
        "statusRuleCode": 0,
        "neutralSite": "",
        "links": [],
        "statcrewGameID": "",
        "eventId": "dsy4h6il2e6dqc3c",
        "fastdate": 1773115200000,
        "streams": [
            {
                "type": 0,
                "provider": ""
            }
        ],
        "address": "",
        "city": "",
        "stateCountry": "",
        "zipCode": "",
        "venue": "",
        "primetime": false,
        "forfeitHome": false,
        "forfeitAway": false,
        "weatherDelay": false,
        "suspended": false,
        "noContest": false,
        "eventType": {
            "code": "postSeason",
            "description": "Post-Season/Play-Offs",
            "statsCount": true
        },
        "conferenceResult": "",
        "resultAsObject": {
            "resolved": false,
            "hasScores": false,
            "numericResults": [],
            "description": "",
            "score": "",
            "winnerLoser": "",
            "descriptionShortWithOT": ""
        },
        "opponent": {
            "name": "NJCAA Region 23 Tournament Semifinal",
            "result": "",
            "teamId": "5f1dn27b5e8a1zz3",
            "winner": false,
            "cleanName": "njcaa region tournament semifinal"
        },
        "us": {
            "name": "Mississippi Gulf Coast Community College",
            "result": "",
            "teamId": "jxkq4mk8bbhnvbfe",
            "winner": false,
            "cleanName": "mississippi gulf coast community col"
        },
        "apresult": "",
        "ap2Result": "",
        "result": {
            "resolved": false,
            "hasScores": false,
            "numericResults": [],
            "description": "",
            "score": "",
            "winnerLoser": "",
            "descriptionShortWithOT": ""
        }
    },
    "eventDateFormattedAriaLabel": "March 10 12:00 AM:"
}