{
    "stats": {},
    "eventDateFormatted": "Oct 18",
    "boxScoreLink": "20251018_t9sn.xml",
    "event": {
        "teams": [
            {
                "name": "SUNY Broome Community College",
                "result": "",
                "teamId": "69ekny9p7ue6z488",
                "winner": false,
                "cleanName": "suny broome community col"
            },
            {
                "name": "Westchester Community College",
                "result": "",
                "teamId": "212fyyb5n5ajchk0",
                "winner": false,
                "cleanName": "westchester community col"
            }
        ],
        "status": "",
        "notes": "",
        "notesShared": "Scrimmage",
        "date": 1760821200000,
        "localTimeZone": "America/New_York",
        "tba": false,
        "home": false,
        "overall": false,
        "conference": false,
        "division": false,
        "regional": false,
        "national": false,
        "inProgress": false,
        "statusCode": -2,
        "cancelled": false,
        "postponed": false,
        "postseason": false,
        "sport": "Basketball",
        "statusRuleCode": 0,
        "neutralSite": "",
        "links": [],
        "statcrewGameID": "",
        "eventId": "t9snrpq5lf39al9x",
        "fastdate": 1760821200000,
        "streams": [
            {
                "type": 0,
                "provider": ""
            }
        ],
        "address": "Valhalla, NY",
        "city": "",
        "stateCountry": "",
        "zipCode": "",
        "venue": "",
        "primetime": false,
        "forfeitHome": false,
        "forfeitAway": false,
        "weatherDelay": false,
        "suspended": false,
        "noContest": false,
        "eventType": {
            "code": "scrimmage",
            "description": "Scrimmage",
            "statsCount": false
        },
        "ap2Result": "",
        "conferenceResult": "",
        "resultAsObject": {
            "resolved": false,
            "hasScores": false,
            "description": "",
            "score": "",
            "numericResults": [],
            "winnerLoser": "",
            "descriptionShortWithOT": ""
        },
        "opponent": {
            "name": "Westchester Community College",
            "result": "",
            "teamId": "212fyyb5n5ajchk0",
            "winner": false,
            "cleanName": "westchester community col"
        },
        "us": {
            "name": "SUNY Broome Community College",
            "result": "",
            "teamId": "69ekny9p7ue6z488",
            "winner": false,
            "cleanName": "suny broome community col"
        },
        "apresult": "",
        "result": {
            "resolved": false,
            "hasScores": false,
            "description": "",
            "score": "",
            "numericResults": [],
            "winnerLoser": "",
            "descriptionShortWithOT": ""
        }
    },
    "eventDateFormattedAriaLabel": "October 18 05:00 PM:"
}