{
    "stats": {
        "ast": "21",
        "fgpt3": "33.3",
        "dreb": "33",
        "topg": "1.4",
        "fgmpm": "12.5",
        "ftptg": ".656",
        "blkpm": "0.5",
        "ftppg": "1.5-2.3",
        "ftppm": "5.5-8.3",
        "dq": "0",
        "fgmpg": "3.4",
        "topm": "5.2",
        "blkpg": "0.1",
        "ftppct": ".656",
        "ato": "1.1",
        "fgptg3": ".333",
        "fgpt3pct": ".333",
        "stl": "11",
        "fgpt": "37.5",
        "minptg": "11.0",
        "fgp3pm": "6.2-18.7",
        "treb": "36",
        "trebpm": "9.4",
        "trebpg": "2.6",
        "fga": "128",
        "fgppm": "12.5-33.2",
        "ftapm": "8.3",
        "ftmpg": "1.5",
        "ptspg": "10.1",
        "pfpm": "6.8",
        "fgm3": "24",
        "fgm3pm": "6.2",
        "fgppg": "3.4-9.1",
        "fga3pg": "5.1",
        "ptspm": "36.6",
        "fgm": "48",
        "fgp": "48-128",
        "ftmpm": "5.5",
        "fgptg": ".375",
        "fta": "32",
        "min": "154",
        "fga3pm": "18.7",
        "fgp3pg": "1.7-5.1",
        "ftapg": "2.3",
        "pfpg": "1.9",
        "ga": "14-11",
        "fga3": "72",
        "ftm": "21",
        "blk": "2",
        "ftpt": "65.6",
        "orebpm": "0.8",
        "stlpm": "2.9",
        "fgptpct": ".375",
        "ftp": "21-32",
        "dqpm": "0.0",
        "orebpg": "0.2",
        "stlpg": "0.8",
        "gp": "14",
        "dqpg": "0.0",
        "fgp3": "24-72",
        "gs": "11",
        "pts": "141",
        "fgapm": "33.2",
        "fgm3pg": "1.7",
        "drebpm": "8.6",
        "astpm": "5.5",
        "oreb": "3",
        "astpg": "1.5",
        "pf": "26",
        "minpg": "11.0",
        "drebpg": "2.4",
        "fgapg": "9.1",
        "to": "20",
        "minpm": "40"
    },
    "statsConference": {
        "fgppm": "0.0-0.0",
        "ftp": "0-0",
        "fgp3pg": "0.0-0.0",
        "ftppg": "0.0-0.0",
        "ga": "0-0",
        "fgp3": "0-0",
        "fgppg": "0.0-0.0",
        "fgp3pm": "0.0-0.0",
        "ftppm": "0.0-0.0",
        "pts": "0",
        "minpm": "40",
        "fgp": "0-0"
    },
    "statsNational": {
        "ast": "11",
        "fgpt3": "35.1",
        "dreb": "24",
        "topg": "1.0",
        "fgmpm": "9.6",
        "ftptg": ".722",
        "blkpm": "0.7",
        "ftppg": "1.6-2.2",
        "ftppm": "4.3-6.0",
        "dq": "0",
        "fgmpg": "3.6",
        "topm": "2.6",
        "blkpg": "0.3",
        "ftppct": ".722",
        "ato": "1.4",
        "fgptg3": ".351",
        "fgpt3pct": ".351",
        "stl": "3",
        "fgpt": "39.2",
        "minptg": "15.1",
        "fgp3pm": "4.3-12.2",
        "treb": "24",
        "trebpm": "7.9",
        "trebpg": "3.0",
        "fga": "74",
        "fgppm": "9.6-24.5",
        "ftapm": "6.0",
        "ftmpg": "1.6",
        "ptspg": "10.5",
        "pfpm": "4.0",
        "fgm3": "13",
        "fgm3pm": "4.3",
        "fgppg": "3.6-9.2",
        "fga3pg": "4.6",
        "ptspm": "27.8",
        "fgm": "29",
        "fgp": "29-74",
        "ftmpm": "4.3",
        "fgptg": ".392",
        "fta": "18",
        "min": "121",
        "fga3pm": "12.2",
        "fgp3pg": "1.6-4.6",
        "ftapg": "2.3",
        "pfpg": "1.5",
        "ga": "8-6",
        "fga3": "37",
        "ftm": "13",
        "blk": "2",
        "ftpt": "72.2",
        "orebpm": "0.0",
        "stlpm": "1.0",
        "fgptpct": ".392",
        "ftp": "13-18",
        "dqpm": "0.0",
        "orebpg": "0.0",
        "stlpg": "0.4",
        "gp": "8",
        "dqpg": "0.0",
        "fgp3": "13-37",
        "gs": "6",
        "pts": "84",
        "fgapm": "24.5",
        "fgm3pg": "1.6",
        "drebpm": "7.9",
        "astpm": "3.6",
        "oreb": "0",
        "astpg": "1.4",
        "pf": "12",
        "minpg": "15.1",
        "drebpg": "3.0",
        "fgapg": "9.3",
        "to": "8",
        "minpm": "40"
    },
    "pageName": "roziahscottbatesbsho",
    "teamPageName": null,
    "firstName": "Ro'Ziah",
    "lastName": "Scott-Bates",
    "team": "Jefferson College",
    "playerId": "bsho4gz4i60x2lvw",
    "teamId": "tar5fy48wxcs5dlw",
    "conference": null,
    "region": "16",
    "dob": null,
    "careerId": null,
    "rank": null,
    "eventCount": 14,
    "lastUpdated": 1766618874000,
    "position": "G",
    "positionAbbreviation": null,
    "positionCode": "G0FR",
    "dataMap": {
        "hometown": "",
        "born": "",
        "weight": "",
        "height": ""
    },
    "uniform": "2",
    "year": "Fr",
    "playerStatus": {
        "enumCode": 1,
        "abbr": "A",
        "statusName": "Active",
        "active": true,
        "interceptFieldCallback": null,
        "nullableType": {
            "comparator": {},
            "returnedClass": "java.lang.Integer",
            "name": "integer",
            "primitiveClass": "int",
            "defaultValue": 0,
            "collectionType": false,
            "mutable": false,
            "componentType": false,
            "entityType": false,
            "associationType": false,
            "xmlelement": false,
            "anyType": false
        },
        "mutable": false
    },
    "active": true,
    "fullName": "Ro'Ziah Scott-Bates",
    "minCalcStats": {
        "fgppm": true,
        "fgpt3": true,
        "topg": true,
        "ptspg": true,
        "pfpm": true,
        "blkpm": true,
        "ftppg": true,
        "fgppg": true,
        "ptspm": true,
        "ftppm": true,
        "topm": true,
        "blkpg": true,
        "fgp3pg": true,
        "pfpg": true,
        "ato": true,
        "ftpt": false,
        "stlpm": true,
        "orebpm": true,
        "stlpg": true,
        "orebpg": true,
        "fgpt": true,
        "fgp3pm": true,
        "trebpm": true,
        "drebpm": true,
        "astpm": true,
        "astpg": true,
        "minpg": true,
        "drebpg": true,
        "trebpg": true,
        "minpm": true
    },
    "minCalcConfStats": {
        "fgppm": false,
        "fgpt3": false,
        "topg": false,
        "ptspg": false,
        "pfpm": false,
        "blkpm": false,
        "ftppg": false,
        "fgppg": false,
        "ptspm": false,
        "ftppm": false,
        "topm": false,
        "blkpg": false,
        "fgp3pg": false,
        "pfpg": false,
        "ato": false,
        "ftpt": false,
        "stlpm": false,
        "orebpm": false,
        "stlpg": false,
        "orebpg": false,
        "fgpt": false,
        "fgp3pm": false,
        "trebpm": false,
        "drebpm": false,
        "astpm": false,
        "astpg": false,
        "minpg": false,
        "drebpg": false,
        "trebpg": false,
        "minpm": false
    },
    "minCalcNationalStats": {
        "fgppm": true,
        "fgpt3": true,
        "topg": true,
        "ptspg": true,
        "pfpm": true,
        "blkpm": true,
        "ftppg": true,
        "fgppg": true,
        "ptspm": true,
        "ftppm": true,
        "topm": true,
        "blkpg": true,
        "fgp3pg": true,
        "pfpg": true,
        "ato": true,
        "ftpt": false,
        "stlpm": true,
        "orebpm": true,
        "stlpg": true,
        "orebpg": true,
        "fgpt": true,
        "fgp3pm": true,
        "trebpm": true,
        "drebpm": true,
        "astpm": true,
        "astpg": true,
        "minpg": true,
        "drebpg": true,
        "trebpg": true,
        "minpm": true
    },
    "minStats": {},
    "minConfStats": {},
    "minNationalStats": {}
}