{
    "stats": {},
    "eventDateFormatted": "Oct 11",
    "boxScoreLink": "20251011_ybyp.xml",
    "event": {
        "teams": [
            {
                "name": "Link Year Prep",
                "result": "",
                "teamId": "mlur9j9x1p97oicm",
                "winner": false,
                "cleanName": "link year prep"
            },
            {
                "name": "Fort Scott Community College",
                "result": "",
                "teamId": "iyl0uvg9ndxu4pru",
                "winner": false,
                "cleanName": "fort scott community col"
            }
        ],
        "status": "",
        "notes": "",
        "notesShared": "Fort Scott ",
        "date": 1760198400000,
        "localTimeZone": "America/Chicago",
        "tba": false,
        "home": true,
        "overall": false,
        "conference": false,
        "division": false,
        "regional": false,
        "national": false,
        "inProgress": false,
        "statusCode": -2,
        "cancelled": false,
        "postponed": false,
        "postseason": false,
        "sport": "Basketball",
        "statusRuleCode": 0,
        "neutralSite": "",
        "links": [],
        "statcrewGameID": "",
        "eventId": "ybypbncikvmpfdd9",
        "fastdate": 1760198400000,
        "streams": [
            {
                "type": 0,
                "provider": ""
            }
        ],
        "address": "",
        "city": "",
        "stateCountry": "",
        "zipCode": "",
        "venue": "",
        "primetime": false,
        "forfeitHome": false,
        "forfeitAway": false,
        "weatherDelay": false,
        "suspended": false,
        "noContest": false,
        "eventType": {
            "code": "scrimmage",
            "description": "Scrimmage",
            "statsCount": false
        },
        "conferenceResult": "",
        "resultAsObject": {
            "resolved": false,
            "hasScores": false,
            "description": "",
            "score": "",
            "numericResults": [],
            "winnerLoser": "",
            "descriptionShortWithOT": ""
        },
        "opponent": {
            "name": "Link Year Prep",
            "result": "",
            "teamId": "mlur9j9x1p97oicm",
            "winner": false,
            "cleanName": "link year prep"
        },
        "us": {
            "name": "Fort Scott Community College",
            "result": "",
            "teamId": "iyl0uvg9ndxu4pru",
            "winner": false,
            "cleanName": "fort scott community col"
        },
        "apresult": "",
        "ap2Result": "",
        "result": {
            "resolved": false,
            "hasScores": false,
            "description": "",
            "score": "",
            "numericResults": [],
            "winnerLoser": "",
            "descriptionShortWithOT": ""
        }
    },
    "eventDateFormattedAriaLabel": "October 11 12:00 PM:"
}