{
    "stats": {
        "ast": "17",
        "fgpt3": "0.0",
        "dreb": "44",
        "topg": "1.1",
        "fgmpm": "24.0",
        "ftptg": ".778",
        "blkpm": "5.3",
        "ftppg": "1.0-1.3",
        "ftppm": "12.4-16.0",
        "fgmpg": "1.9",
        "topm": "14.2",
        "blkpg": "0.4",
        "ftppct": ".778",
        "ato": "1.1",
        "fgptg3": ".000",
        "fgpt3pct": ".000",
        "stl": "4",
        "fgpt": "50.0",
        "minptg": "3.2",
        "fgp3pm": "0.0-1.8",
        "treb": "64",
        "trebpm": "56.9",
        "trebpg": "4.6",
        "fga": "54",
        "fgppm": "24.0-48.0",
        "ftapm": "16.0",
        "ftmpg": "1.0",
        "ptspg": "4.9",
        "pfpm": "13.3",
        "fgm3": "0",
        "fgm3pm": "0.0",
        "fgppg": "1.9-3.9",
        "fga3pg": "0.1",
        "ptspm": "60.4",
        "fgm": "27",
        "fgp": "27-54",
        "ftmpm": "12.4",
        "fgptg": ".500",
        "fta": "18",
        "min": "45",
        "fga3pm": "1.8",
        "fgp3pg": "0.0-0.1",
        "ftapg": "1.3",
        "pfpg": "1.1",
        "ga": "14-5",
        "fga3": "2",
        "ftm": "14",
        "blk": "6",
        "ftpt": "77.8",
        "orebpm": "17.8",
        "stlpm": "3.6",
        "fgptpct": ".500",
        "ftp": "14-18",
        "dqpm": "0.0",
        "orebpg": "1.4",
        "stlpg": "0.3",
        "gp": "14",
        "fgp3": "0-2",
        "gs": "5",
        "pts": "68",
        "fgapm": "48.0",
        "fgm3pg": "0.0",
        "drebpm": "39.1",
        "astpm": "15.1",
        "oreb": "20",
        "astpg": "1.2",
        "pf": "15",
        "minpg": "3.2",
        "drebpg": "3.1",
        "fgapg": "3.9",
        "to": "16",
        "minpm": "40"
    },
    "statsConference": {
        "ast": "5",
        "dreb": "16",
        "topg": "1.3",
        "fgmpm": "120.0",
        "ftptg": ".571",
        "blkpm": "40.0",
        "ftppg": "1.3-2.3",
        "ftppm": "53.3-93.3",
        "fgmpg": "3.0",
        "topm": "53.3",
        "blkpg": "1.0",
        "ftppct": ".571",
        "ato": "1.3",
        "stl": "1",
        "fgpt": "69.2",
        "minptg": "1.0",
        "fgp3pm": "0.0-0.0",
        "treb": "22",
        "trebpm": "293.3",
        "trebpg": "7.3",
        "fga": "13",
        "fgppm": "120.0-173.3",
        "ftapm": "93.3",
        "ftmpg": "1.3",
        "ptspg": "7.3",
        "pfpm": "0.0",
        "fgm3": "0",
        "fgm3pm": "0.0",
        "fgppg": "3.0-4.3",
        "fga3pg": "0.0",
        "ptspm": "293.3",
        "fgm": "9",
        "fgp": "9-13",
        "ftmpm": "53.3",
        "fgptg": ".692",
        "fta": "7",
        "min": "3",
        "fga3pm": "0.0",
        "fgp3pg": "0.0-0.0",
        "ftapg": "2.3",
        "pfpg": "0.0",
        "ga": "3-3",
        "fga3": "0",
        "ftm": "4",
        "blk": "3",
        "ftpt": "57.1",
        "orebpm": "80.0",
        "stlpm": "13.3",
        "fgptpct": ".692",
        "ftp": "4-7",
        "dqpm": "0.0",
        "orebpg": "2.0",
        "stlpg": "0.3",
        "gp": "3",
        "fgp3": "0-0",
        "gs": "3",
        "pts": "22",
        "fgapm": "173.3",
        "fgm3pg": "0.0",
        "drebpm": "213.3",
        "astpm": "66.7",
        "oreb": "6",
        "astpg": "1.7",
        "pf": "0",
        "minpg": "1.0",
        "drebpg": "5.3",
        "fgapg": "4.3",
        "to": "4",
        "minpm": "40"
    },
    "statsNational": {
        "ast": "10",
        "dreb": "31",
        "topg": "1.0",
        "fgmpm": "16.0",
        "ftptg": ".750",
        "blkpm": "4.0",
        "ftppg": "1.0-1.3",
        "ftppm": "9.0-12.0",
        "fgmpg": "1.8",
        "topm": "9.0",
        "blkpg": "0.4",
        "ftppct": ".750",
        "ato": "1.1",
        "stl": "2",
        "fgpt": "53.3",
        "minptg": "4.4",
        "fgp3pm": "0.0-0.0",
        "treb": "44",
        "trebpm": "44.0",
        "trebpg": "4.9",
        "fga": "30",
        "fgppm": "16.0-30.0",
        "ftapm": "12.0",
        "ftmpg": "1.0",
        "ptspg": "4.6",
        "pfpm": "8.0",
        "fgm3": "0",
        "fgm3pm": "0.0",
        "fgppg": "1.8-3.3",
        "fga3pg": "0.0",
        "ptspm": "41.0",
        "fgm": "16",
        "fgp": "16-30",
        "ftmpm": "9.0",
        "fgptg": ".533",
        "fta": "12",
        "min": "40",
        "fga3pm": "0.0",
        "fgp3pg": "0.0-0.0",
        "ftapg": "1.3",
        "pfpg": "0.9",
        "ga": "9-5",
        "fga3": "0",
        "ftm": "9",
        "blk": "4",
        "ftpt": "75.0",
        "orebpm": "13.0",
        "stlpm": "2.0",
        "fgptpct": ".533",
        "ftp": "9-12",
        "dqpm": "0.0",
        "orebpg": "1.4",
        "stlpg": "0.2",
        "gp": "9",
        "fgp3": "0-0",
        "gs": "5",
        "pts": "41",
        "fgapm": "30.0",
        "fgm3pg": "0.0",
        "drebpm": "31.0",
        "astpm": "10.0",
        "oreb": "13",
        "astpg": "1.1",
        "pf": "8",
        "minpg": "4.4",
        "drebpg": "3.4",
        "fgapg": "3.3",
        "to": "9",
        "minpm": "40"
    },
    "pageName": "anshumandeoray8o9",
    "teamPageName": null,
    "firstName": "Anshuman",
    "lastName": "Deora",
    "team": "Dallas College Brookhaven",
    "playerId": "y8o9zgyb5l6hfsbi",
    "teamId": "ct1vwsco373ledhq",
    "conference": null,
    "region": "5",
    "dob": null,
    "careerId": null,
    "rank": null,
    "eventCount": 14,
    "lastUpdated": 1766007371000,
    "position": "C",
    "positionAbbreviation": "C",
    "positionCode": null,
    "dataMap": {
        "hometown": "India",
        "born": "",
        "weight": "",
        "height": "6'8"
    },
    "uniform": "14",
    "year": "So",
    "playerStatus": {
        "enumCode": 1,
        "abbr": "A",
        "statusName": "Active",
        "active": true,
        "interceptFieldCallback": null,
        "nullableType": {
            "comparator": {},
            "returnedClass": "java.lang.Integer",
            "name": "integer",
            "primitiveClass": "int",
            "defaultValue": 0,
            "mutable": false,
            "collectionType": false,
            "componentType": false,
            "entityType": false,
            "associationType": false,
            "xmlelement": false,
            "anyType": false
        },
        "mutable": false
    },
    "active": true,
    "fullName": "Anshuman Deora",
    "minCalcStats": {
        "fgppm": false,
        "fgpt3": false,
        "topg": true,
        "ptspg": true,
        "pfpm": false,
        "blkpm": false,
        "ftppg": true,
        "fgppg": true,
        "ptspm": false,
        "ftppm": false,
        "topm": false,
        "blkpg": true,
        "fgp3pg": true,
        "pfpg": true,
        "ato": true,
        "ftpt": false,
        "stlpm": false,
        "orebpm": false,
        "stlpg": true,
        "orebpg": true,
        "fgpt": false,
        "fgp3pm": false,
        "trebpm": false,
        "drebpm": false,
        "astpm": false,
        "astpg": true,
        "minpg": true,
        "drebpg": true,
        "trebpg": true,
        "minpm": false
    },
    "minCalcConfStats": {
        "fgppm": false,
        "fgpt3": false,
        "topg": true,
        "ptspg": true,
        "pfpm": false,
        "blkpm": false,
        "ftppg": true,
        "fgppg": true,
        "ptspm": false,
        "ftppm": false,
        "topm": false,
        "blkpg": true,
        "fgp3pg": true,
        "pfpg": true,
        "ato": true,
        "ftpt": false,
        "stlpm": false,
        "orebpm": false,
        "stlpg": true,
        "orebpg": true,
        "fgpt": true,
        "fgp3pm": false,
        "trebpm": false,
        "drebpm": false,
        "astpm": false,
        "astpg": true,
        "minpg": true,
        "drebpg": true,
        "trebpg": true,
        "minpm": false
    },
    "minCalcNationalStats": {
        "fgppm": false,
        "fgpt3": false,
        "topg": true,
        "ptspg": true,
        "pfpm": false,
        "blkpm": false,
        "ftppg": true,
        "fgppg": true,
        "ptspm": false,
        "ftppm": false,
        "topm": false,
        "blkpg": true,
        "fgp3pg": true,
        "pfpg": true,
        "ato": true,
        "ftpt": false,
        "stlpm": false,
        "orebpm": false,
        "stlpg": true,
        "orebpg": true,
        "fgpt": false,
        "fgp3pm": false,
        "trebpm": false,
        "drebpm": false,
        "astpm": false,
        "astpg": true,
        "minpg": true,
        "drebpg": true,
        "trebpg": true,
        "minpm": false
    },
    "minStats": {},
    "minConfStats": {},
    "minNationalStats": {}
}