{
    "stats": {
        "ast": "16",
        "fgpt3": "46.3",
        "dreb": "60",
        "topg": "0.9",
        "fgmpm": "181.5",
        "ftptg": ".688",
        "blkpm": "21.5",
        "ftppg": "1.7-2.5",
        "ftppm": "67.7-98.5",
        "fgmpg": "4.5",
        "topm": "36.9",
        "blkpg": "0.5",
        "ftppct": ".688",
        "ato": "1.3",
        "fgptg3": ".463",
        "fgpt3pct": ".463",
        "stl": "12",
        "fgpt": "46.5",
        "minptg": "1.0",
        "fgp3pm": "95.4-206.2",
        "treb": "92",
        "trebpm": "283.1",
        "trebpg": "7.1",
        "fga": "127",
        "fgppm": "181.5-390.8",
        "ftapm": "98.5",
        "ftmpg": "1.7",
        "ptspg": "13.2",
        "pfpm": "67.7",
        "fgm3": "31",
        "fgm3pm": "95.4",
        "fgppg": "4.5-9.8",
        "fga3pg": "5.2",
        "ptspm": "526.2",
        "fgm": "59",
        "fgp": "59-127",
        "ftmpm": "67.7",
        "fgptg": ".465",
        "fta": "32",
        "min": "13",
        "fga3pm": "206.2",
        "fgp3pg": "2.4-5.2",
        "ftapg": "2.5",
        "pfpg": "1.7",
        "ga": "13-13",
        "fga3": "67",
        "ftm": "22",
        "blk": "7",
        "ftpt": "68.8",
        "orebpm": "98.5",
        "stlpm": "36.9",
        "fgptpct": ".465",
        "ftp": "22-32",
        "dqpm": "0.0",
        "orebpg": "2.5",
        "stlpg": "0.9",
        "gp": "13",
        "fgp3": "31-67",
        "gs": "13",
        "pts": "171",
        "fgapm": "390.8",
        "fgm3pg": "2.4",
        "drebpm": "184.6",
        "astpm": "49.2",
        "oreb": "32",
        "astpg": "1.2",
        "pf": "22",
        "minpg": "1.0",
        "drebpg": "4.6",
        "fgapg": "9.8",
        "to": "12",
        "minpm": "40"
    },
    "statsConference": {
        "fgppm": "0.0-0.0",
        "ftp": "0-0",
        "fgp3pg": "0.0-0.0",
        "ftppg": "0.0-0.0",
        "ga": "0-0",
        "fgp3": "0-0",
        "fgppg": "0.0-0.0",
        "fgp3pm": "0.0-0.0",
        "ftppm": "0.0-0.0",
        "pts": "0",
        "minpm": "40",
        "fgp": "0-0"
    },
    "statsNational": {
        "ast": "10",
        "fgpt3": "40.0",
        "dreb": "38",
        "topg": "0.9",
        "fgmpm": "155.0",
        "ftptg": ".739",
        "blkpm": "25.0",
        "ftppg": "2.1-2.9",
        "ftppm": "85.0-115.0",
        "fgmpg": "3.9",
        "topm": "35.0",
        "blkpg": "0.6",
        "ftppct": ".739",
        "ato": "1.4",
        "fgptg3": ".400",
        "fgpt3pct": ".400",
        "stl": "9",
        "fgpt": "38.8",
        "minptg": "1.0",
        "fgp3pm": "90.0-225.0",
        "treb": "56",
        "trebpm": "280.0",
        "trebpg": "7.0",
        "fga": "80",
        "fgppm": "155.0-400.0",
        "ftapm": "115.0",
        "ftmpg": "2.1",
        "ptspg": "12.1",
        "pfpm": "95.0",
        "fgm3": "18",
        "fgm3pm": "90.0",
        "fgppg": "3.9-10.0",
        "fga3pg": "5.6",
        "ptspm": "485.0",
        "fgm": "31",
        "fgp": "31-80",
        "ftmpm": "85.0",
        "fgptg": ".388",
        "fta": "23",
        "min": "8",
        "fga3pm": "225.0",
        "fgp3pg": "2.2-5.6",
        "ftapg": "2.9",
        "pfpg": "2.4",
        "ga": "8-8",
        "fga3": "45",
        "ftm": "17",
        "blk": "5",
        "ftpt": "73.9",
        "orebpm": "90.0",
        "stlpm": "45.0",
        "fgptpct": ".388",
        "ftp": "17-23",
        "dqpm": "0.0",
        "orebpg": "2.3",
        "stlpg": "1.1",
        "gp": "8",
        "fgp3": "18-45",
        "gs": "8",
        "pts": "97",
        "fgapm": "400.0",
        "fgm3pg": "2.3",
        "drebpm": "190.0",
        "astpm": "50.0",
        "oreb": "18",
        "astpg": "1.3",
        "pf": "19",
        "minpg": "1.0",
        "drebpg": "4.8",
        "fgapg": "10.0",
        "to": "7",
        "minpm": "40"
    },
    "pageName": "ryanevansx2j9",
    "teamPageName": null,
    "firstName": "Ryan",
    "lastName": "Evans",
    "team": "Gaston College",
    "playerId": "x2j96wqor84swooa",
    "teamId": "bav4kxva1lutes5f",
    "conference": null,
    "region": "10",
    "dob": null,
    "careerId": null,
    "rank": null,
    "eventCount": 13,
    "lastUpdated": 1766245170000,
    "position": "G/F",
    "positionAbbreviation": "G/F",
    "positionCode": null,
    "dataMap": {},
    "uniform": "7",
    "year": "So.",
    "playerStatus": {
        "enumCode": 1,
        "abbr": "A",
        "statusName": "Active",
        "active": true,
        "interceptFieldCallback": null,
        "nullableType": {
            "comparator": {},
            "returnedClass": "java.lang.Integer",
            "name": "integer",
            "primitiveClass": "int",
            "defaultValue": 0,
            "mutable": false,
            "componentType": false,
            "collectionType": false,
            "anyType": false,
            "entityType": false,
            "associationType": false,
            "xmlelement": false
        },
        "mutable": false
    },
    "active": true,
    "fullName": "Ryan Evans",
    "minCalcStats": {
        "fgppm": false,
        "fgpt3": true,
        "topg": true,
        "ptspg": true,
        "pfpm": false,
        "blkpm": false,
        "ftppg": true,
        "fgppg": true,
        "ptspm": false,
        "ftppm": false,
        "topm": false,
        "blkpg": true,
        "fgp3pg": true,
        "pfpg": true,
        "ato": true,
        "ftpt": false,
        "stlpm": false,
        "orebpm": false,
        "stlpg": true,
        "orebpg": true,
        "fgpt": true,
        "fgp3pm": false,
        "trebpm": false,
        "drebpm": false,
        "astpm": false,
        "astpg": true,
        "minpg": true,
        "drebpg": true,
        "trebpg": true,
        "minpm": false
    },
    "minCalcConfStats": {
        "fgppm": false,
        "fgpt3": false,
        "topg": false,
        "ptspg": false,
        "pfpm": false,
        "blkpm": false,
        "ftppg": false,
        "fgppg": false,
        "ptspm": false,
        "ftppm": false,
        "topm": false,
        "blkpg": false,
        "fgp3pg": false,
        "pfpg": false,
        "ato": false,
        "ftpt": false,
        "stlpm": false,
        "orebpm": false,
        "stlpg": false,
        "orebpg": false,
        "fgpt": false,
        "fgp3pm": false,
        "trebpm": false,
        "drebpm": false,
        "astpm": false,
        "astpg": false,
        "minpg": false,
        "drebpg": false,
        "trebpg": false,
        "minpm": false
    },
    "minCalcNationalStats": {
        "fgppm": false,
        "fgpt3": true,
        "topg": true,
        "ptspg": true,
        "pfpm": false,
        "blkpm": false,
        "ftppg": true,
        "fgppg": true,
        "ptspm": false,
        "ftppm": false,
        "topm": false,
        "blkpg": true,
        "fgp3pg": true,
        "pfpg": true,
        "ato": true,
        "ftpt": true,
        "stlpm": false,
        "orebpm": false,
        "stlpg": true,
        "orebpg": true,
        "fgpt": true,
        "fgp3pm": false,
        "trebpm": false,
        "drebpm": false,
        "astpm": false,
        "astpg": true,
        "minpg": true,
        "drebpg": true,
        "trebpg": true,
        "minpm": false
    },
    "minStats": {},
    "minConfStats": {},
    "minNationalStats": {}
}