{
    "stats": {
        "ast": "5",
        "fgpt3": "50.0",
        "dreb": "18",
        "topg": "0.8",
        "fgmpm": "3.9",
        "blkpm": "0.3",
        "ftppg": "0.0-0.0",
        "ftppm": "0.0-0.0",
        "fgmpg": "2.0",
        "topm": "1.6",
        "blkpg": "0.2",
        "ato": "1.0",
        "fgptg3": ".500",
        "fgpt3pct": ".500",
        "stl": "3",
        "fgpt": "41.4",
        "minptg": "20.3",
        "fgp3pm": "2.0-3.9",
        "treb": "20",
        "trebpm": "6.6",
        "trebpg": "3.3",
        "fga": "29",
        "fgppm": "3.9-9.5",
        "ftapm": "0.0",
        "ftmpg": "0.0",
        "ptspg": "5.0",
        "pfpm": "3.0",
        "fgm3": "6",
        "fgm3pm": "2.0",
        "fgppg": "2.0-4.8",
        "fga3pg": "2.0",
        "ptspm": "9.8",
        "fgm": "12",
        "fgp": "12-29",
        "ftmpm": "0.0",
        "fgptg": ".414",
        "fta": "0",
        "min": "122",
        "fga3pm": "3.9",
        "fgp3pg": "1.0-2.0",
        "ftapg": "0.0",
        "pfpg": "1.5",
        "ga": "6-5",
        "fga3": "12",
        "ftm": "0",
        "blk": "1",
        "orebpm": "0.7",
        "stlpm": "1.0",
        "fgptpct": ".414",
        "ftp": "0-0",
        "dqpm": "0.0",
        "orebpg": "0.3",
        "stlpg": "0.5",
        "gp": "6",
        "fgp3": "6-12",
        "gs": "5",
        "pts": "30",
        "fgapm": "9.5",
        "fgm3pg": "1.0",
        "drebpm": "5.9",
        "astpm": "1.6",
        "oreb": "2",
        "astpg": "0.8",
        "pf": "9",
        "minpg": "20.3",
        "drebpg": "3.0",
        "fgapg": "4.8",
        "to": "5",
        "minpm": "40"
    },
    "statsConference": {
        "fgppm": "0.0-0.0",
        "ftp": "0-0",
        "fgp3pg": "0.0-0.0",
        "ftppg": "0.0-0.0",
        "ga": "0-0",
        "fgp3": "0-0",
        "fgppg": "0.0-0.0",
        "fgp3pm": "0.0-0.0",
        "ftppm": "0.0-0.0",
        "pts": "0",
        "minpm": "40",
        "fgp": "0-0"
    },
    "statsNational": {
        "ast": "5",
        "fgpt3": "50.0",
        "dreb": "18",
        "topg": "0.8",
        "fgmpm": "3.9",
        "blkpm": "0.3",
        "ftppg": "0.0-0.0",
        "ftppm": "0.0-0.0",
        "fgmpg": "2.0",
        "topm": "1.6",
        "blkpg": "0.2",
        "ato": "1.0",
        "fgptg3": ".500",
        "fgpt3pct": ".500",
        "stl": "3",
        "fgpt": "41.4",
        "minptg": "20.3",
        "fgp3pm": "2.0-3.9",
        "treb": "20",
        "trebpm": "6.6",
        "trebpg": "3.3",
        "fga": "29",
        "fgppm": "3.9-9.5",
        "ftapm": "0.0",
        "ftmpg": "0.0",
        "ptspg": "5.0",
        "pfpm": "3.0",
        "fgm3": "6",
        "fgm3pm": "2.0",
        "fgppg": "2.0-4.8",
        "fga3pg": "2.0",
        "ptspm": "9.8",
        "fgm": "12",
        "fgp": "12-29",
        "ftmpm": "0.0",
        "fgptg": ".414",
        "fta": "0",
        "min": "122",
        "fga3pm": "3.9",
        "fgp3pg": "1.0-2.0",
        "ftapg": "0.0",
        "pfpg": "1.5",
        "ga": "6-5",
        "fga3": "12",
        "ftm": "0",
        "blk": "1",
        "orebpm": "0.7",
        "stlpm": "1.0",
        "fgptpct": ".414",
        "ftp": "0-0",
        "dqpm": "0.0",
        "orebpg": "0.3",
        "stlpg": "0.5",
        "gp": "6",
        "fgp3": "6-12",
        "gs": "5",
        "pts": "30",
        "fgapm": "9.5",
        "fgm3pg": "1.0",
        "drebpm": "5.9",
        "astpm": "1.6",
        "oreb": "2",
        "astpg": "0.8",
        "pf": "9",
        "minpg": "20.3",
        "drebpg": "3.0",
        "fgapg": "4.8",
        "to": "5",
        "minpm": "40"
    },
    "pageName": "brandonbossertf72b",
    "teamPageName": null,
    "firstName": "Brandon",
    "lastName": "Bossert",
    "team": "Delta College",
    "playerId": "f72bsv3m3yf7yvbq",
    "teamId": "2yxlcx1vv1teaytn",
    "conference": null,
    "region": "12",
    "dob": null,
    "careerId": null,
    "rank": null,
    "eventCount": 7,
    "lastUpdated": 1766436468000,
    "position": "G",
    "positionAbbreviation": "G",
    "positionCode": null,
    "dataMap": {},
    "uniform": "15",
    "year": "FR",
    "playerStatus": {
        "enumCode": 1,
        "abbr": "A",
        "statusName": "Active",
        "active": true,
        "interceptFieldCallback": null,
        "nullableType": {
            "comparator": {},
            "returnedClass": "java.lang.Integer",
            "name": "integer",
            "primitiveClass": "int",
            "defaultValue": 0,
            "mutable": false,
            "componentType": false,
            "collectionType": false,
            "entityType": false,
            "associationType": false,
            "xmlelement": false,
            "anyType": false
        },
        "mutable": false
    },
    "active": true,
    "fullName": "Brandon Bossert",
    "minCalcStats": {
        "fgppm": true,
        "fgpt3": false,
        "topg": false,
        "ptspg": false,
        "pfpm": true,
        "blkpm": true,
        "ftppg": false,
        "fgppg": false,
        "ptspm": true,
        "ftppm": true,
        "topm": true,
        "blkpg": false,
        "fgp3pg": false,
        "pfpg": false,
        "ato": false,
        "ftpt": false,
        "stlpm": true,
        "orebpm": true,
        "stlpg": false,
        "orebpg": false,
        "fgpt": false,
        "fgp3pm": true,
        "trebpm": true,
        "drebpm": true,
        "astpm": true,
        "astpg": false,
        "minpg": false,
        "drebpg": false,
        "trebpg": false,
        "minpm": true
    },
    "minCalcConfStats": {
        "fgppm": false,
        "fgpt3": false,
        "topg": false,
        "ptspg": false,
        "pfpm": false,
        "blkpm": false,
        "ftppg": false,
        "fgppg": false,
        "ptspm": false,
        "ftppm": false,
        "topm": false,
        "blkpg": false,
        "fgp3pg": false,
        "pfpg": false,
        "ato": false,
        "ftpt": false,
        "stlpm": false,
        "orebpm": false,
        "stlpg": false,
        "orebpg": false,
        "fgpt": false,
        "fgp3pm": false,
        "trebpm": false,
        "drebpm": false,
        "astpm": false,
        "astpg": false,
        "minpg": false,
        "drebpg": false,
        "trebpg": false,
        "minpm": false
    },
    "minCalcNationalStats": {
        "fgppm": true,
        "fgpt3": false,
        "topg": false,
        "ptspg": false,
        "pfpm": true,
        "blkpm": true,
        "ftppg": false,
        "fgppg": false,
        "ptspm": true,
        "ftppm": true,
        "topm": true,
        "blkpg": false,
        "fgp3pg": false,
        "pfpg": false,
        "ato": false,
        "ftpt": false,
        "stlpm": true,
        "orebpm": true,
        "stlpg": false,
        "orebpg": false,
        "fgpt": false,
        "fgp3pm": true,
        "trebpm": true,
        "drebpm": true,
        "astpm": true,
        "astpg": false,
        "minpg": false,
        "drebpg": false,
        "trebpg": false,
        "minpm": true
    },
    "minStats": {},
    "minConfStats": {},
    "minNationalStats": {}
}